.gitignore
LICENSE.txt
MANIFEST.in
README.md
requirements.txt
setup.py
config_files/test_config.yaml
gixi/__init__.py
gixi/__main__.py
gixi/package_info.py
gixi.egg-info/PKG-INFO
gixi.egg-info/SOURCES.txt
gixi.egg-info/dependency_links.txt
gixi.egg-info/requires.txt
gixi.egg-info/top_level.txt
gixi/client/__init__.py
gixi/client/__main__.py
gixi/client/cif_viewer.py
gixi/client/config_list.py
gixi/client/config_widget.py
gixi/client/data_holder.py
gixi/client/exception_message.py
gixi/client/file_tab.py
gixi/client/file_viewer.py
gixi/client/h5file_viewer.py
gixi/client/h5utils.py
gixi/client/image_tab.py
gixi/client/image_viewer.py
gixi/client/main_window.py
gixi/client/polar_viewer.py
gixi/client/radial_profiles.py
gixi/client/read_cifs.py
gixi/client/rois.py
gixi/client/submit_job.py
gixi/client/tools.py
gixi/client/basic_widgets/__init__.py
gixi/client/basic_widgets/labels.py
gixi/client/basic_widgets/plots_2d.py
gixi/client/basic_widgets/progress_bar.py
gixi/client/basic_widgets/sliders.py
gixi/client/basic_widgets/spinner.py
gixi/client/basic_widgets/toolbars.py
gixi/client/logs/__init__.py
gixi/client/logs/log_config.py
gixi/client/logs/log_handler.py
gixi/client/logs/log_widget.py
gixi/client/logs/server_log_widget.py
gixi/server/__init__.py
gixi/server/__main__.py
gixi/server/app_config.py
gixi/server/config.py
gixi/server/connect_peaks.py
gixi/server/h5utils.py
gixi/server/log_config.py
gixi/server/misc.py
gixi/server/models_collection.py
gixi/server/parallelize_ops.py
gixi/server/run.py
gixi/server/server_operations.py
gixi/server/time_record.py
gixi/server/basic_simulations/__init__.py
gixi/server/basic_simulations/fast_simulation.py
gixi/server/basic_simulations/misc.py
gixi/server/basic_simulations/sim_dataset.py
gixi/server/img_processing/__init__.py
gixi/server/img_processing/angle_limits.py
gixi/server/img_processing/contrast_correction.py
gixi/server/img_processing/conversions.py
gixi/server/img_processing/he.py
gixi/server/img_processing/utils.py
gixi/server/matching/__init__.py
gixi/server/matching/match_patterns.py
gixi/server/matching/simulate_diffraction_peaks.py
