Metadata-Version: 2.1
Name: gixi
Version: 0.0.1
Summary: GIXD feature detection for Maxwell cluster at DESY synchrotron
Home-page: UNKNOWN
Author: Vladimir Starostin
Author-email: vladimir.starostin@uni-tuebingen.de
License: GPLv3
Platform: UNKNOWN
Classifier: Development Status :: 3 - Alpha
Classifier: Intended Audience :: Science/Research
Classifier: Programming Language :: Python :: 3
Classifier: Programming Language :: Python :: 3.6
Classifier: Programming Language :: Python :: 3.7
Classifier: Programming Language :: Python :: 3.8
Classifier: Programming Language :: Python :: 3.9
Requires-Python: >=3.6
License-File: LICENSE.txt
